swiftetl/__init__.py
swiftetl/etl_pipeline.py
swiftetl-0.1.0.dist-info/LICENSE
swiftetl-0.1.0.dist-info/METADATA
swiftetl-0.1.0.dist-info/WHEEL
swiftetl-0.1.0.dist-info/top_level.txt
swiftetl-0.1.0.dist-info/RECORD
